rm-protection/protect.py
rm-protection/rm_p.py
rm_protection/__init__.py
rm_protection/config.py
rm_protection/protect.py
rm_protection/rm_p.py
rm_protection-0.1.3.dist-info/DESCRIPTION.rst
rm_protection-0.1.3.dist-info/METADATA
rm_protection-0.1.3.dist-info/RECORD
rm_protection-0.1.3.dist-info/WHEEL
rm_protection-0.1.3.dist-info/entry_points.txt
rm_protection-0.1.3.dist-info/metadata.json
rm_protection-0.1.3.dist-info/top_level.txt
