Metadata-Version: 2.0
Name: rm-protection
Version: 0.1.3
Summary: A safe alternative for "rm" with minimum difference.
Home-page: https://github.com/alanzchen/rm-protection
Author: Alan Chen
Author-email: me@zenan.ch
License: MIT
Platform: UNKNOWN
Classifier: License :: OSI Approved :: MIT License
Classifier: Intended Audience :: Developers
Classifier: Programming Language :: Python :: 2
Classifier: Programming Language :: Python :: 3
Classifier: Programming Language :: Python :: Implementation :: CPython
Classifier: Programming Language :: Python :: Implementation :: PyPy
Classifier: Topic :: System
Requires-Dist: future
